overrides_/__init__.py
overrides_/enforce.py
overrides_/final.py
overrides_/overrides.py
radgraph/__init__.py
radgraph/radgraph.py
radgraph/rewards.py
radgraph/utils.py
radgraph/allennlp/__init__.py
radgraph/allennlp/__main__.py
radgraph/allennlp/version.py
radgraph/allennlp/commands/__init__.py
radgraph/allennlp/commands/evaluate.py
radgraph/allennlp/commands/find_learning_rate.py
radgraph/allennlp/commands/predict.py
radgraph/allennlp/commands/print_results.py
radgraph/allennlp/commands/subcommand.py
radgraph/allennlp/commands/test_install.py
radgraph/allennlp/commands/train.py
radgraph/allennlp/common/__init__.py
radgraph/allennlp/common/cached_transformers.py
radgraph/allennlp/common/checks.py
radgraph/allennlp/common/file_utils.py
radgraph/allennlp/common/from_params.py
radgraph/allennlp/common/lazy.py
radgraph/allennlp/common/logging.py
radgraph/allennlp/common/params.py
radgraph/allennlp/common/plugins.py
radgraph/allennlp/common/registrable.py
radgraph/allennlp/common/tqdm.py
radgraph/allennlp/common/util.py
radgraph/allennlp/common/testing/__init__.py
radgraph/allennlp/common/testing/distributed_test.py
radgraph/allennlp/common/testing/model_test_case.py
radgraph/allennlp/common/testing/test_case.py
radgraph/allennlp/data/__init__.py
radgraph/allennlp/data/batch.py
radgraph/allennlp/data/dataloader.py
radgraph/allennlp/data/instance.py
radgraph/allennlp/data/vocabulary.py
radgraph/allennlp/data/dataset_readers/__init__.py
radgraph/allennlp/data/dataset_readers/babi.py
radgraph/allennlp/data/dataset_readers/conll2003.py
radgraph/allennlp/data/dataset_readers/dataset_reader.py
radgraph/allennlp/data/dataset_readers/interleaving_dataset_reader.py
radgraph/allennlp/data/dataset_readers/sequence_tagging.py
radgraph/allennlp/data/dataset_readers/sharded_dataset_reader.py
radgraph/allennlp/data/dataset_readers/text_classification_json.py
radgraph/allennlp/data/dataset_readers/dataset_utils/__init__.py
radgraph-0.1.0.dist-info/METADATA
radgraph-0.1.0.dist-info/WHEEL
radgraph-0.1.0.dist-info/top_level.txt
radgraph-0.1.0.dist-info/RECORD
