Metadata-Version: 2.1
Name: radgraph
Version: 0.1.0
Author: Jean-Benoit Delbrouck
License: MIT
Classifier: Intended Audience :: Science/Research
Classifier: Topic :: Scientific/Engineering
Classifier: License :: OSI Approved :: MIT License
Classifier: Programming Language :: Python :: 3 :: Only
Requires-Dist: torch >=1.8.1
Requires-Dist: transformers >=4.23.1
Requires-Dist: appdirs
Requires-Dist: jsonpickle
Requires-Dist: filelock
Requires-Dist: h5py
Requires-Dist: spacy
Requires-Dist: nltk
Requires-Dist: dotmap
